katiag_image_processing/__init__.py
katiag_image_processing/processing/__init__.py
katiag_image_processing/processing/combination.py
katiag_image_processing/processing/transformation.py
katiag_image_processing/utils/__init__.py
katiag_image_processing/utils/io.py
katiag_image_processing/utils/plot.py
katiag_image_processing-0.0.1.dist-info/METADATA
katiag_image_processing-0.0.1.dist-info/WHEEL
katiag_image_processing-0.0.1.dist-info/top_level.txt
katiag_image_processing-0.0.1.dist-info/RECORD
