Metadata-Version: 2.1
Name: katiag_image_processing
Version: 0.0.1
Summary: Image Processing Package using Skimage
Home-page: https://github.com/kriskacg/katiag-image-processing-package
Author: Katia
Requires-Python: >=3.12.5
Requires-Dist: matplotlib
Requires-Dist: numpy
Requires-Dist: scikit-image >=0.16.1
